README.md
setup.py
lfc/__init__.py
lfc.egg-info/PKG-INFO
lfc.egg-info/SOURCES.txt
lfc.egg-info/dependency_links.txt
lfc.egg-info/top_level.txt